rand/__init__.py
rand/providers/__init__.py
rand/providers/base.py
rand/providers/contribs/__init__.py
rand/providers/contribs/faker.py
rand/providers/ds/__init__.py
rand/providers/ds/ds.py
rand/providers/en/__init__.py
rand/rand.py
rand-0.2.0.dist-info/LICENSE
rand-0.2.0.dist-info/WHEEL
rand-0.2.0.dist-info/METADATA
rand-0.2.0.dist-info/RECORD
