Metadata-Version: 2.1
Name: rand
Version: 0.2.0
Summary: Generate String from regex pattern
Home-page: https://github.com/kororo/rand
License: MIT
Keywords: random,generator,string,regex
Author: kororo
Requires-Python: >=3.6,<4.0
Classifier: License :: OSI Approved :: MIT License
Classifier: Programming Language :: Python :: 3
Classifier: Programming Language :: Python :: 3.6
Classifier: Programming Language :: Python :: 3.7
Classifier: Programming Language :: Python :: 3.8
Provides-Extra: test
Requires-Dist: peewee (>=3.13.3,<4.0.0)
Requires-Dist: pytest-cov (>=2.0,<3.0)
Project-URL: Repository, https://github.com/kororo/rand
